{
    "data": [{"word":"abstract","pos":"a","meaning":"추상적인, 난해한"},
{"word":"abstract","pos":"n","meaning":"개요"},
{"word":"abstract","pos":"v","meaning":"발췌하다 ; 요약하다"},
{"word":"accommodate","pos":"v","meaning":"공급하다 ; 수용하다 ;적응시키다, 조절하다"},
{"word":"actual","pos":"a","meaning":"현실의, 실재의"},
{"word":"acute","pos":"a","meaning":"날카로운, 예리한 ; 극심한"},
{"word":"administer","pos":"v","meaning":"관리하다 ; 실시하다"},
{"word":"advantage","pos":"n","meaning":"장점, 이점 ; 유리, 이익"},
{"word":"afford","pos":"v","meaning":"주다,제공하다 ; 여유가 되다"},
{"word":"aggressive","pos":"a","meaning":"공격적인, 적극적인"},
{"word":"alert","pos":"a","meaning":"경계하는 ; 깨어있는"},
{"word":"alert","pos":"v","meaning":"경고하다"},
{"word":"allude","pos":"v","meaning":"언급하다, 암시하다, 비추다"},
{"word":"alter","pos":"v","meaning":"바꾸다, 변경하다"},
{"word":"amaze","pos":"v","meaning":"몹시 놀라게 하다"},
{"word":"ample","pos":"a","meaning":"충분한 ; 넓은"},
{"word":"animate","pos":"v","meaning":"활기를 주다"},
{"word":"antipathy","pos":"n","meaning":"반감, 혐오"},
{"word":"apply","pos":"v","meaning":"적용하다 , 쓰다"},
{"word":"approach","pos":"n","meaning":"접근, 해결 방법"},
{"word":"approach","pos":"v","meaning":"접근하다"},
{"word":"approve","pos":"v","meaning":"찬성하다, 승인하다"},
{"word":"aristocracy","pos":"n","meaning":"귀족"},
{"word":"article","pos":"n","meaning":"(개개의) 물품 ; 기사, 논설 ; 조항 (법)"},
{"word":"assent","pos":"v","meaning":"동의하다, 찬성하다"},
{"word":"astronomy","pos":"n","meaning":"천문학"},
{"word":"atmosphere","pos":"n","meaning":"공기, 분위기"},
{"word":"attempt","pos":"v","meaning":"시도하다"},
{"word":"attempt","pos":"n","meaning":"시도"},
{"word":"bait","pos":"n","meaning":"미끼, 유혹"},
{"word":"bait","pos":"v","meaning":"미끼로 꾀다"},
{"word":"banish","pos":"v","meaning":"(국외로) 추방하다, ~를 몰아내다"},
{"word":"behalf","pos":"n","meaning":"위함, 이익"},
{"word":"biography","pos":"n","meaning":"전기, 일대기"},
{"word":"blame","pos":"v","meaning":"나무라다, 비난하다"},
{"word":"boss","pos":"n","meaning":"우두머리, 사장"},
{"word":"broke","pos":"a","meaning":"한푼 없는, 빈털터리의, 파산한"},
{"word":"capacity","pos":"n","meaning":"용적, 수용력 ; 능력, 재능"},
{"word":"cease","pos":"v","meaning":"멈추다, 그만두다"},
{"word":"coat","pos":"v","meaning":"표면을 덮다"},
{"word":"coat","pos":"n","meaning":"외투(코트)"},
{"word":"command","pos":"v","meaning":"명령하다, 지시하다"},
{"word":"command","pos":"n","meaning":"명령"},
{"word":"commerce","pos":"n","meaning":"교역, 상업"},
{"word":"commodity","pos":"n","meaning":"상품, 산물"},
{"word":"complex","pos":"a","meaning":"정교한, 복잡한, 어려운"},
{"word":"complex","pos":"n","meaning":"복합건물"},
{"word":"confer","pos":"v","meaning":"수여하다, 주다 ; 의논하다"},
{"word":"conform","pos":"v","meaning":"순응하다, 따르다"},
{"word":"conservative","pos":"a","meaning":"보수적인"},
{"word":"consume","pos":"v","meaning":"다 써버리다, 소모하다"},
{"word":"contribute","pos":"v","meaning":"공헌하다"},
{"word":"convenience","pos":"n","meaning":"편리"},
{"word":"convention","pos":"n","meaning":"회의, 인습"},
{"word":"copy","pos":"n","meaning":"복사, 복제"},
{"word":"copy","pos":"v","meaning":"복사하다"},
{"word":"cradle","pos":"n","meaning":"요람 ; 발상지"},
{"word":"crime","pos":"n","meaning":"죄, 범죄"},
{"word":"crude","pos":"a","meaning":"가공하지 않은, 투박한"},
{"word":"decorate","pos":"v","meaning":"장식하다"},
{"word":"deliver","pos":"v","meaning":"배달하다 ; ~을 말하다 , 전달하다"},
{"word":"demonstrate","pos":"v","meaning":"증명하다, (모형으로) 설명하다"},
{"word":"despair","pos":"n","meaning":"절망, 자포자기"},
{"word":"despair","pos":"v","meaning":"절망하다, 체념하다"},
{"word":"destitute","pos":"a","meaning":"빈곤한"},
{"word":"detail","pos":"n","meaning":"상세"},
{"word":"determine","pos":"v","meaning":"결심(결정)하다"},
{"word":"device","pos":"n","meaning":"장치"},
{"word":"discourse","pos":"n","meaning":"이야기, 담화"},
{"word":"disguise","pos":"v","meaning":"변장하다"},
{"word":"disguise","pos":"n","meaning":"변장, 가장"},
{"word":"diverse","pos":"a","meaning":"다양한"},
{"word":"domain","pos":"n","meaning":"영토, 분야"},
{"word":"earn","pos":"v","meaning":"벌다, 획득하다, 얻다"},
{"word":"elegance","pos":"n","meaning":"우아함"},
{"word":"eminent","pos":"a","meaning":"저명한, 탁월한"},
{"word":"endow","pos":"v","meaning":"~에게 주다 ; 기부하다"},
{"word":"enterprise","pos":"n","meaning":"(모험적인) 사업"},
{"word":"enthusiasm","pos":"n","meaning":"의욕, 열의, 열광, 열심"},
{"word":"entrust","pos":"v","meaning":"위임하다"},
{"word":"exertion","pos":"n","meaning":"노력"},
{"word":"exhibit","pos":"v","meaning":"진열하다, 내보이다"},
{"word":"expedition","pos":"n","meaning":"탐험(대)"},
{"word":"extravagant","pos":"a","meaning":"낭비벽이 있는 ; 터무니 없는, 지나친"},
{"word":"faint","pos":"a","meaning":"희미한 ; 나약한"},
{"word":"faint","pos":"v","meaning":"기절하다"},
{"word":"fertile","pos":"a","meaning":"비옥한, 풍부한"},
{"word":"forbear","pos":"v","meaning":"참고 견디다, 삼가다"},
{"word":"fortitude","pos":"n","meaning":"인내 ; 용기"},
{"word":"found","pos":"v","meaning":"창설하다, 설립하다"},
{"word":"full","pos":"a","meaning":"완전한 ;가득 찬"},
{"word":"gravity","pos":"n","meaning":"중력, 인력"},
{"word":"great","pos":"a","meaning":"큰, 중대한, 위대한"},
{"word":"guilty","pos":"a","meaning":"죄를 범한, 유죄의"},
{"word":"guilty","pos":"n","meaning":"죄책감, 죄악감"},
{"word":"haste","pos":"n","meaning":"서두름"},
{"word":"homage","pos":"n","meaning":"경의"},
{"word":"ignorance","pos":"n","meaning":"무지"},
{"word":"imagination","pos":"n","meaning":"상상(력)"},
{"word":"immense","pos":"a","meaning":"거대한, 매우 큰"},
{"word":"incessant","pos":"a","meaning":"끊임없는, 쉴새없는"},
{"word":"incident","pos":"n","meaning":"사건"},
{"word":"indicate","pos":"v","meaning":"보여주다, 나타내다"},
{"word":"induce","pos":"v","meaning":"야기하다, 유발하다; 꼬시다, 설득하다"},
{"word":"infect","pos":"v","meaning":"전염시키다"},
{"word":"ingenious","pos":"a","meaning":"영리한, 독창적인"},
{"word":"intrude","pos":"v","meaning":"침입하다 ; 방해하다"},
{"word":"invert","pos":"v","meaning":"~을 거꾸로 하다, 뒤집다"},
{"word":"involve","pos":"v","meaning":"포함하다, 수반하다 ; 연루되다"},
{"word":"laboratory","pos":"n","meaning":"실험실, 연구소"},
{"word":"logic","pos":"n","meaning":"논리"},
{"word":"look","pos":"v","meaning":"보다, 주목하다 ;살피다"},
{"word":"look","pos":"n","meaning":"보기"},
{"word":"magic","pos":"n","meaning":"마술, 마력"},
{"word":"majesty","pos":"n","meaning":"존엄, 폐하"},
{"word":"material","pos":"a","meaning":"물질의, 구체적인"},
{"word":"material","pos":"n","meaning":"재료, 요소 ; 자료"},
{"word":"mechanism","pos":"n","meaning":"도구 ; 구조"},
{"word":"merchandise","pos":"n","meaning":"상품"},
{"word":"merit","pos":"n","meaning":"장점, 우수함"},
{"word":"merit","pos":"v","meaning":"~할 만하다"},
{"word":"military","pos":"a","meaning":"군대의, 육군의"},
{"word":"military","pos":"n","meaning":"군대"},
{"word":"miser","pos":"n","meaning":"구두쇠, 수전노"},
{"word":"mock","pos":"v","meaning":"조롱하다"},
{"word":"mortal","pos":"a","meaning":"죽을 수 밖에 없는 운명의 ; 치명적인"},
{"word":"motive","pos":"n","meaning":"동기, 목적"},
{"word":"multitude","pos":"n","meaning":"다수, 군중"},
{"word":"naked","pos":"a","meaning":"벌거숭이의, 나체의"},
{"word":"nightmare","pos":"n","meaning":"악몽"},
{"word":"occasion","pos":"n","meaning":"경우 ; 사건, 특별한 일"},
{"word":"oracle","pos":"n","meaning":"신탁(神託), 신의 응답"},
{"word":"ordinary","pos":"a","meaning":"보통의, 일상적인, 평범한"},
{"word":"outlook","pos":"n","meaning":"전망, 견해"},
{"word":"partial","pos":"a","meaning":"일부분의, 부분적인 ; 불공평한"},
{"word":"pasture","pos":"n","meaning":"목장, 목초지"},
{"word":"persist","pos":"v","meaning":"지속하다 ; 고집하다, 주장하다"},
{"word":"plain","pos":"a","meaning":"솔직한, 분명한 ; 꾸밈없는, 간소한"},
{"word":"plain","pos":"n","meaning":"평원,평지"},
{"word":"poison","pos":"n","meaning":"독"},
{"word":"poison","pos":"v","meaning":"독살하다"},
{"word":"popularity","pos":"n","meaning":"인기, 유행"},
{"word":"positive","pos":"a","meaning":"긍정적인; 확고한, 명백한"},
{"word":"postpone","pos":"v","meaning":"연기하다, 미루다"},
{"word":"potential","pos":"a","meaning":"잠재적인, 가능한"},
{"word":"potential","pos":"n","meaning":"잠재력"},
{"word":"praise","pos":"n","meaning":"칭찬, 숭배"},
{"word":"praise","pos":"v","meaning":"칭찬하다"},
{"word":"predecessor","pos":"n","meaning":"전임자, 선배, 선조"},
{"word":"predict","pos":"v","meaning":"예견하다"},
{"word":"preserve","pos":"v","meaning":"보존하다, 보호하다 ; 지속하다, 유지하다"},
{"word":"preserve","pos":"n","meaning":"금렵지, 보호지"},
{"word":"pride","pos":"n","meaning":"자랑, 자만심"},
{"word":"prime","pos":"n","meaning":"전성(기) ; 소수(수학)"},
{"word":"prime","pos":"a","meaning":"주요한"},
{"word":"profit","pos":"n","meaning":"이익"},
{"word":"profit","pos":"v","meaning":"이익을 보다"},
{"word":"progress","pos":"n","meaning":"전진, 진보"},
{"word":"progress","pos":"v","meaning":"전진하다, 진보하다"},
{"word":"protest","pos":"v","meaning":"항의하다 ; 단언하다, 주장하다"},
{"word":"protest","pos":"n","meaning":"항의, 시위"},
{"word":"providence","pos":"n","meaning":"섭리, 신의 뜻, 신"},
{"word":"publish","pos":"v","meaning":"발표하다 ; 출판하다"},
{"word":"rare","pos":"a","meaning":"드문, 진기한"},
{"word":"ray","pos":"n","meaning":"광선"},
{"word":"reap","pos":"v","meaning":"얻다, 거두다"},
{"word":"reconcile","pos":"v","meaning":"화해시키다"},
{"word":"reduce","pos":"v","meaning":"줄이다, 감소시키다"},
{"word":"refresh","pos":"v","meaning":"상쾌하게 하다, 새롭게 하다"},
{"word":"rejoice","pos":"v","meaning":"기뻐하다 ; 기쁘게하다"},
{"word":"relish","pos":"n","meaning":"(큰) 즐거움 기쁨; 소스, 조미료, 양념"},
{"word":"relish","pos":"v","meaning":"( 어떤것을 대단히) 좋아하다, 즐기다"},
{"word":"remedy","pos":"n","meaning":"치료, 요법"},
{"word":"remedy","pos":"v","meaning":"고치다, 치료하다"},
{"word":"renounce","pos":"v","meaning":"버리다, 부인하다"},
{"word":"reproach","pos":"v","meaning":"비난하다, 꾸짖다"},
{"word":"reproach","pos":"n","meaning":"비난, 잔소리"},
{"word":"resemble","pos":"v","meaning":"닮다"},
{"word":"resort","pos":"n","meaning":"휴양지 ; 수단"},
{"word":"resort","pos":"v","meaning":"의지, 의존하다 (대안이 없어서 하는)"},
{"word":"restrict","pos":"v","meaning":"제한하다, 한정하다"},
{"word":"riot","pos":"n","meaning":"폭동, 소동"},
{"word":"rumor","pos":"n","meaning":"소문"},
{"word":"run","pos":"v","meaning":"달리다; 경영하다; (물) 흐르다"},
{"word":"ruthless","pos":"a","meaning":"무자비한, 무정한"},
{"word":"sacrifice","pos":"n","meaning":"희생"},
{"word":"sacrifice","pos":"v","meaning":"희생하다"},
{"word":"salute","pos":"n","meaning":"인사, 경례"},
{"word":"salute","pos":"v","meaning":"인사하다, 경례하다"},
{"word":"scale","pos":"v","meaning":"오르다 ; 저울에 달다"},
{"word":"scale","pos":"n","meaning":"규모 ; 비늘"},
{"word":"scatter","pos":"v","meaning":"흩뿌리다"},
{"word":"scrutiny","pos":"n","meaning":"정밀조사"},
{"word":"seclude","pos":"v","meaning":"분리하다, 격리하다"},
{"word":"seek","pos":"v","meaning":"찾다, 추구하다 ; 노력하다"},
{"word":"sensitive","pos":"a","meaning":"민감한"},
{"word":"sermon","pos":"n","meaning":"설교"},
{"word":"shabby","pos":"a","meaning":"허름한, 초라한"},
{"word":"singular","pos":"a","meaning":"단수의, 개인의"},
{"word":"skeptical","pos":"a","meaning":"의심 많은, 회의적인"},
{"word":"soul","pos":"n","meaning":"영혼, 사람"},
{"word":"spare","pos":"a","meaning":"부가적인, 추가의"},
{"word":"spare","pos":"v","meaning":"(시간, 돈)등을 내주다 ; 절약하다"},
{"word":"spectacle","pos":"n","meaning":"(인상적인) 광경"},
{"word":"stately","pos":"a","meaning":"당당한, 품위있는"},
{"word":"status","pos":"n","meaning":"지위, 신분 ; 현재상황"},
{"word":"steep","pos":"a","meaning":"가파른"},
{"word":"steep","pos":"n","meaning":"절벽"},
{"word":"steer","pos":"v","meaning":"조종하다 ; 나아가다"},
{"word":"stiff","pos":"a","meaning":"굳은, 뻣뻣한 ; 어려운"},
{"word":"stimulus","pos":"n","meaning":"자극, 격려"},
{"word":"subside","pos":"v","meaning":"진정되다"},
{"word":"summit","pos":"n","meaning":"정상, 꼭대기"},
{"word":"support","pos":"v","meaning":"유지하다, 지지하다 ; 부양하다"},
{"word":"support","pos":"n","meaning":"지원,지지; 생계"},
{"word":"suppress","pos":"v","meaning":"억압하다"},
{"word":"surpass","pos":"v","meaning":"능가하다, ~보다 낫다"},
{"word":"surplus","pos":"n","meaning":"나머지, 잔여"},
{"word":"sustain","pos":"v","meaning":"지탱하다 ; 유지하다"},
{"word":"symptom","pos":"n","meaning":"징조, 징후"},
{"word":"tall","pos":"a","meaning":"키가 큰, 높이가 ~인"},
{"word":"tedious","pos":"a","meaning":"지루한, 싫증나는"},
{"word":"tell","pos":"v","meaning":"말하다"},
{"word":"temporary","pos":"a","meaning":"일시적인, 임시의"},
{"word":"territory","pos":"n","meaning":"영토"},
{"word":"testimony","pos":"n","meaning":"증거, 증명"},
{"word":"tidy","pos":"a","meaning":"단정한"},
{"word":"tip","pos":"n","meaning":"끝, 첨단 ; 힌트"},
{"word":"unprecedented","pos":"a","meaning":"선례가 없는"},
{"word":"uphold","pos":"v","meaning":"지지하다, 떠받다"},
{"word":"victory","pos":"n","meaning":"승리"},
{"word":"vile","pos":"a","meaning":"사악한"},
{"word":"vision","pos":"n","meaning":"시력 ; 선견지명"},
{"word":"warfare","pos":"n","meaning":"전쟁"},
{"word":"wholesome","pos":"a","meaning":"건강에 좋은"},
{"word":"will","pos":"n","meaning":"의지, 유언장"},
{"word":"will","pos":"aux. v","meaning":"~ 할 것이다"},
{"word":"withhold","pos":"v","meaning":"보류하다 ; 억제하다, 억누르다"}]}